{
  "method": "summed_attention_ablation_incremental",
  "model_key": "instruct",
  "model_name": "meta-llama/Meta-Llama-3-8B-Instruct",
  "question": "inc_year",
  "question_prompt": "What year was the company incorporated?",
  "total_tokens": 2048,
  "test_samples": 32,
  "ablation_levels": [
    5,
    10,
    20,
    30,
    40,
    50
  ],
  "heads_source": "phase2_summed_attention_results",
  "timestamp": "2026-02-05T04:17:23.915472",
  "baseline": {
    "accuracy": 0.9375,
    "correct": 30,
    "total": 32
  },
  "top_heads_ablations": [
    {
      "num_heads": 5,
      "heads": [
        [
          20,
          25
        ],
        [
          16,
          1
        ],
        [
          14,
          31
        ],
        [
          17,
          24
        ],
        [
          18,
          20
        ]
      ],
      "heads_str": [
        "L20H25",
        "L16H1",
        "L14H31",
        "L17H24",
        "L18H20"
      ],
      "accuracy": 0.9375,
      "accuracy_drop": 0.0,
      "correct": 30,
      "total": 32
    },
    {
      "num_heads": 10,
      "heads": [
        [
          20,
          25
        ],
        [
          16,
          1
        ],
        [
          14,
          31
        ],
        [
          17,
          24
        ],
        [
          18,
          20
        ],
        [
          20,
          1
        ],
        [
          22,
          13
        ],
        [
          13,
          18
        ],
        [
          14,
          20
        ],
        [
          14,
          30
        ]
      ],
      "heads_str": [
        "L20H25",
        "L16H1",
        "L14H31",
        "L17H24",
        "L18H20",
        "L20H1",
        "L22H13",
        "L13H18",
        "L14H20",
        "L14H30"
      ],
      "accuracy": 0.25,
      "accuracy_drop": 0.6875,
      "correct": 8,
      "total": 32
    },
    {
      "num_heads": 20,
      "heads": [
        [
          20,
          25
        ],
        [
          16,
          1
        ],
        [
          14,
          31
        ],
        [
          17,
          24
        ],
        [
          18,
          20
        ],
        [
          20,
          1
        ],
        [
          22,
          13
        ],
        [
          13,
          18
        ],
        [
          14,
          20
        ],
        [
          14,
          30
        ],
        [
          23,
          25
        ],
        [
          20,
          26
        ],
        [
          18,
          22
        ],
        [
          16,
          19
        ],
        [
          0,
          28
        ],
        [
          16,
          26
        ],
        [
          0,
          22
        ],
        [
          24,
          27
        ],
        [
          14,
          22
        ],
        [
          19,
          0
        ]
      ],
      "heads_str": [
        "L20H25",
        "L16H1",
        "L14H31",
        "L17H24",
        "L18H20",
        "L20H1",
        "L22H13",
        "L13H18",
        "L14H20",
        "L14H30",
        "L23H25",
        "L20H26",
        "L18H22",
        "L16H19",
        "L0H28",
        "L16H26",
        "L0H22",
        "L24H27",
        "L14H22",
        "L19H0"
      ],
      "accuracy": 0.53125,
      "accuracy_drop": 0.40625,
      "correct": 17,
      "total": 32
    },
    {
      "num_heads": 30,
      "heads": [
        [
          20,
          25
        ],
        [
          16,
          1
        ],
        [
          14,
          31
        ],
        [
          17,
          24
        ],
        [
          18,
          20
        ],
        [
          20,
          1
        ],
        [
          22,
          13
        ],
        [
          13,
          18
        ],
        [
          14,
          20
        ],
        [
          14,
          30
        ],
        [
          23,
          25
        ],
        [
          20,
          26
        ],
        [
          18,
          22
        ],
        [
          16,
          19
        ],
        [
          0,
          28
        ],
        [
          16,
          26
        ],
        [
          0,
          22
        ],
        [
          24,
          27
        ],
        [
          14,
          22
        ],
        [
          19,
          0
        ],
        [
          13,
          17
        ],
        [
          20,
          14
        ],
        [
          16,
          8
        ],
        [
          0,
          30
        ],
        [
          22,
          12
        ],
        [
          0,
          21
        ],
        [
          17,
          26
        ],
        [
          20,
          23
        ],
        [
          17,
          21
        ],
        [
          22,
          29
        ]
      ],
      "heads_str": [
        "L20H25",
        "L16H1",
        "L14H31",
        "L17H24",
        "L18H20",
        "L20H1",
        "L22H13",
        "L13H18",
        "L14H20",
        "L14H30",
        "L23H25",
        "L20H26",
        "L18H22",
        "L16H19",
        "L0H28",
        "L16H26",
        "L0H22",
        "L24H27",
        "L14H22",
        "L19H0",
        "L13H17",
        "L20H14",
        "L16H8",
        "L0H30",
        "L22H12",
        "L0H21",
        "L17H26",
        "L20H23",
        "L17H21",
        "L22H29"
      ],
      "accuracy": 0.875,
      "accuracy_drop": 0.0625,
      "correct": 28,
      "total": 32
    },
    {
      "num_heads": 40,
      "heads": [
        [
          20,
          25
        ],
        [
          16,
          1
        ],
        [
          14,
          31
        ],
        [
          17,
          24
        ],
        [
          18,
          20
        ],
        [
          20,
          1
        ],
        [
          22,
          13
        ],
        [
          13,
          18
        ],
        [
          14,
          20
        ],
        [
          14,
          30
        ],
        [
          23,
          25
        ],
        [
          20,
          26
        ],
        [
          18,
          22
        ],
        [
          16,
          19
        ],
        [
          0,
          28
        ],
        [
          16,
          26
        ],
        [
          0,
          22
        ],
        [
          24,
          27
        ],
        [
          14,
          22
        ],
        [
          19,
          0
        ],
        [
          13,
          17
        ],
        [
          20,
          14
        ],
        [
          16,
          8
        ],
        [
          0,
          30
        ],
        [
          22,
          12
        ],
        [
          0,
          21
        ],
        [
          17,
          26
        ],
        [
          20,
          23
        ],
        [
          17,
          21
        ],
        [
          22,
          29
        ],
        [
          22,
          15
        ],
        [
          27,
          6
        ],
        [
          16,
          0
        ],
        [
          22,
          14
        ],
        [
          13,
          5
        ],
        [
          17,
          27
        ],
        [
          19,
          3
        ],
        [
          27,
          7
        ],
        [
          23,
          14
        ],
        [
          19,
          14
        ]
      ],
      "heads_str": [
        "L20H25",
        "L16H1",
        "L14H31",
        "L17H24",
        "L18H20",
        "L20H1",
        "L22H13",
        "L13H18",
        "L14H20",
        "L14H30",
        "L23H25",
        "L20H26",
        "L18H22",
        "L16H19",
        "L0H28",
        "L16H26",
        "L0H22",
        "L24H27",
        "L14H22",
        "L19H0",
        "L13H17",
        "L20H14",
        "L16H8",
        "L0H30",
        "L22H12",
        "L0H21",
        "L17H26",
        "L20H23",
        "L17H21",
        "L22H29",
        "L22H15",
        "L27H6",
        "L16H0",
        "L22H14",
        "L13H5",
        "L17H27",
        "L19H3",
        "L27H7",
        "L23H14",
        "L19H14"
      ],
      "accuracy": 0.75,
      "accuracy_drop": 0.1875,
      "correct": 24,
      "total": 32
    },
    {
      "num_heads": 50,
      "heads": [
        [
          20,
          25
        ],
        [
          16,
          1
        ],
        [
          14,
          31
        ],
        [
          17,
          24
        ],
        [
          18,
          20
        ],
        [
          20,
          1
        ],
        [
          22,
          13
        ],
        [
          13,
          18
        ],
        [
          14,
          20
        ],
        [
          14,
          30
        ],
        [
          23,
          25
        ],
        [
          20,
          26
        ],
        [
          18,
          22
        ],
        [
          16,
          19
        ],
        [
          0,
          28
        ],
        [
          16,
          26
        ],
        [
          0,
          22
        ],
        [
          24,
          27
        ],
        [
          14,
          22
        ],
        [
          19,
          0
        ],
        [
          13,
          17
        ],
        [
          20,
          14
        ],
        [
          16,
          8
        ],
        [
          0,
          30
        ],
        [
          22,
          12
        ],
        [
          0,
          21
        ],
        [
          17,
          26
        ],
        [
          20,
          23
        ],
        [
          17,
          21
        ],
        [
          22,
          29
        ],
        [
          22,
          15
        ],
        [
          27,
          6
        ],
        [
          16,
          0
        ],
        [
          22,
          14
        ],
        [
          13,
          5
        ],
        [
          17,
          27
        ],
        [
          19,
          3
        ],
        [
          27,
          7
        ],
        [
          23,
          14
        ],
        [
          19,
          14
        ],
        [
          27,
          5
        ],
        [
          19,
          9
        ],
        [
          0,
          13
        ],
        [
          19,
          13
        ],
        [
          13,
          21
        ],
        [
          13,
          30
        ],
        [
          0,
          19
        ],
        [
          27,
          21
        ],
        [
          24,
          24
        ],
        [
          13,
          1
        ]
      ],
      "heads_str": [
        "L20H25",
        "L16H1",
        "L14H31",
        "L17H24",
        "L18H20",
        "L20H1",
        "L22H13",
        "L13H18",
        "L14H20",
        "L14H30",
        "L23H25",
        "L20H26",
        "L18H22",
        "L16H19",
        "L0H28",
        "L16H26",
        "L0H22",
        "L24H27",
        "L14H22",
        "L19H0",
        "L13H17",
        "L20H14",
        "L16H8",
        "L0H30",
        "L22H12",
        "L0H21",
        "L17H26",
        "L20H23",
        "L17H21",
        "L22H29",
        "L22H15",
        "L27H6",
        "L16H0",
        "L22H14",
        "L13H5",
        "L17H27",
        "L19H3",
        "L27H7",
        "L23H14",
        "L19H14",
        "L27H5",
        "L19H9",
        "L0H13",
        "L19H13",
        "L13H21",
        "L13H30",
        "L0H19",
        "L27H21",
        "L24H24",
        "L13H1"
      ],
      "accuracy": 0.625,
      "accuracy_drop": 0.3125,
      "correct": 20,
      "total": 32
    }
  ],
  "random_heads_ablations": [
    {
      "num_heads": 5,
      "heads": [
        [
          21,
          19
        ],
        [
          3,
          24
        ],
        [
          0,
          31
        ],
        [
          25,
          5
        ],
        [
          8,
          31
        ]
      ],
      "heads_str": [
        "L21H19",
        "L3H24",
        "L0H31",
        "L25H5",
        "L8H31"
      ],
      "accuracy": 0.9375,
      "accuracy_drop": 0.0,
      "correct": 30,
      "total": 32
    },
    {
      "num_heads": 10,
      "heads": [
        [
          21,
          19
        ],
        [
          3,
          24
        ],
        [
          0,
          31
        ],
        [
          25,
          5
        ],
        [
          8,
          31
        ],
        [
          8,
          0
        ],
        [
          7,
          10
        ],
        [
          4,
          20
        ],
        [
          25,
          0
        ],
        [
          3,
          14
        ]
      ],
      "heads_str": [
        "L21H19",
        "L3H24",
        "L0H31",
        "L25H5",
        "L8H31",
        "L8H0",
        "L7H10",
        "L4H20",
        "L25H0",
        "L3H14"
      ],
      "accuracy": 0.9375,
      "accuracy_drop": 0.0,
      "correct": 30,
      "total": 32
    },
    {
      "num_heads": 20,
      "heads": [
        [
          21,
          19
        ],
        [
          3,
          24
        ],
        [
          0,
          31
        ],
        [
          25,
          5
        ],
        [
          8,
          31
        ],
        [
          8,
          0
        ],
        [
          7,
          10
        ],
        [
          4,
          20
        ],
        [
          25,
          0
        ],
        [
          3,
          14
        ],
        [
          22,
          30
        ],
        [
          25,
          4
        ],
        [
          30,
          3
        ],
        [
          18,
          7
        ],
        [
          2,
          31
        ],
        [
          19,
          28
        ],
        [
          13,
          27
        ],
        [
          1,
          6
        ],
        [
          1,
          4
        ],
        [
          3,
          5
        ]
      ],
      "heads_str": [
        "L21H19",
        "L3H24",
        "L0H31",
        "L25H5",
        "L8H31",
        "L8H0",
        "L7H10",
        "L4H20",
        "L25H0",
        "L3H14",
        "L22H30",
        "L25H4",
        "L30H3",
        "L18H7",
        "L2H31",
        "L19H28",
        "L13H27",
        "L1H6",
        "L1H4",
        "L3H5"
      ],
      "accuracy": 0.90625,
      "accuracy_drop": 0.03125,
      "correct": 29,
      "total": 32
    },
    {
      "num_heads": 30,
      "heads": [
        [
          21,
          19
        ],
        [
          3,
          24
        ],
        [
          0,
          31
        ],
        [
          25,
          5
        ],
        [
          8,
          31
        ],
        [
          8,
          0
        ],
        [
          7,
          10
        ],
        [
          4,
          20
        ],
        [
          25,
          0
        ],
        [
          3,
          14
        ],
        [
          22,
          30
        ],
        [
          25,
          4
        ],
        [
          30,
          3
        ],
        [
          18,
          7
        ],
        [
          2,
          31
        ],
        [
          19,
          28
        ],
        [
          13,
          27
        ],
        [
          1,
          6
        ],
        [
          1,
          4
        ],
        [
          3,
          5
        ],
        [
          7,
          5
        ],
        [
          7,
          20
        ],
        [
          16,
          25
        ],
        [
          20,
          9
        ],
        [
          1,
          1
        ],
        [
          18,
          25
        ],
        [
          6,
          17
        ],
        [
          24,
          9
        ],
        [
          21,
          30
        ],
        [
          23,
          26
        ]
      ],
      "heads_str": [
        "L21H19",
        "L3H24",
        "L0H31",
        "L25H5",
        "L8H31",
        "L8H0",
        "L7H10",
        "L4H20",
        "L25H0",
        "L3H14",
        "L22H30",
        "L25H4",
        "L30H3",
        "L18H7",
        "L2H31",
        "L19H28",
        "L13H27",
        "L1H6",
        "L1H4",
        "L3H5",
        "L7H5",
        "L7H20",
        "L16H25",
        "L20H9",
        "L1H1",
        "L18H25",
        "L6H17",
        "L24H9",
        "L21H30",
        "L23H26"
      ],
      "accuracy": 0.90625,
      "accuracy_drop": 0.03125,
      "correct": 29,
      "total": 32
    },
    {
      "num_heads": 40,
      "heads": [
        [
          21,
          19
        ],
        [
          3,
          24
        ],
        [
          0,
          31
        ],
        [
          25,
          5
        ],
        [
          8,
          31
        ],
        [
          8,
          0
        ],
        [
          7,
          10
        ],
        [
          4,
          20
        ],
        [
          25,
          0
        ],
        [
          3,
          14
        ],
        [
          22,
          30
        ],
        [
          25,
          4
        ],
        [
          30,
          3
        ],
        [
          18,
          7
        ],
        [
          2,
          31
        ],
        [
          19,
          28
        ],
        [
          13,
          27
        ],
        [
          1,
          6
        ],
        [
          1,
          4
        ],
        [
          3,
          5
        ],
        [
          7,
          5
        ],
        [
          7,
          20
        ],
        [
          16,
          25
        ],
        [
          20,
          9
        ],
        [
          1,
          1
        ],
        [
          18,
          25
        ],
        [
          6,
          17
        ],
        [
          24,
          9
        ],
        [
          21,
          30
        ],
        [
          23,
          26
        ],
        [
          13,
          24
        ],
        [
          7,
          7
        ],
        [
          14,
          25
        ],
        [
          19,
          27
        ],
        [
          9,
          2
        ],
        [
          27,
          13
        ],
        [
          29,
          12
        ],
        [
          0,
          6
        ],
        [
          25,
          23
        ],
        [
          27,
          10
        ]
      ],
      "heads_str": [
        "L21H19",
        "L3H24",
        "L0H31",
        "L25H5",
        "L8H31",
        "L8H0",
        "L7H10",
        "L4H20",
        "L25H0",
        "L3H14",
        "L22H30",
        "L25H4",
        "L30H3",
        "L18H7",
        "L2H31",
        "L19H28",
        "L13H27",
        "L1H6",
        "L1H4",
        "L3H5",
        "L7H5",
        "L7H20",
        "L16H25",
        "L20H9",
        "L1H1",
        "L18H25",
        "L6H17",
        "L24H9",
        "L21H30",
        "L23H26",
        "L13H24",
        "L7H7",
        "L14H25",
        "L19H27",
        "L9H2",
        "L27H13",
        "L29H12",
        "L0H6",
        "L25H23",
        "L27H10"
      ],
      "accuracy": 0.8125,
      "accuracy_drop": 0.125,
      "correct": 26,
      "total": 32
    },
    {
      "num_heads": 50,
      "heads": [
        [
          21,
          19
        ],
        [
          3,
          24
        ],
        [
          0,
          31
        ],
        [
          25,
          5
        ],
        [
          8,
          31
        ],
        [
          8,
          0
        ],
        [
          7,
          10
        ],
        [
          4,
          20
        ],
        [
          25,
          0
        ],
        [
          3,
          14
        ],
        [
          22,
          30
        ],
        [
          25,
          4
        ],
        [
          30,
          3
        ],
        [
          18,
          7
        ],
        [
          2,
          31
        ],
        [
          19,
          28
        ],
        [
          13,
          27
        ],
        [
          1,
          6
        ],
        [
          1,
          4
        ],
        [
          3,
          5
        ],
        [
          7,
          5
        ],
        [
          7,
          20
        ],
        [
          16,
          25
        ],
        [
          20,
          9
        ],
        [
          1,
          1
        ],
        [
          18,
          25
        ],
        [
          6,
          17
        ],
        [
          24,
          9
        ],
        [
          21,
          30
        ],
        [
          23,
          26
        ],
        [
          13,
          24
        ],
        [
          7,
          7
        ],
        [
          14,
          25
        ],
        [
          19,
          27
        ],
        [
          9,
          2
        ],
        [
          27,
          13
        ],
        [
          29,
          12
        ],
        [
          0,
          6
        ],
        [
          25,
          23
        ],
        [
          27,
          10
        ],
        [
          5,
          9
        ],
        [
          23,
          21
        ],
        [
          11,
          2
        ],
        [
          5,
          5
        ],
        [
          7,
          2
        ],
        [
          25,
          27
        ],
        [
          10,
          30
        ],
        [
          3,
          4
        ],
        [
          12,
          11
        ],
        [
          3,
          9
        ]
      ],
      "heads_str": [
        "L21H19",
        "L3H24",
        "L0H31",
        "L25H5",
        "L8H31",
        "L8H0",
        "L7H10",
        "L4H20",
        "L25H0",
        "L3H14",
        "L22H30",
        "L25H4",
        "L30H3",
        "L18H7",
        "L2H31",
        "L19H28",
        "L13H27",
        "L1H6",
        "L1H4",
        "L3H5",
        "L7H5",
        "L7H20",
        "L16H25",
        "L20H9",
        "L1H1",
        "L18H25",
        "L6H17",
        "L24H9",
        "L21H30",
        "L23H26",
        "L13H24",
        "L7H7",
        "L14H25",
        "L19H27",
        "L9H2",
        "L27H13",
        "L29H12",
        "L0H6",
        "L25H23",
        "L27H10",
        "L5H9",
        "L23H21",
        "L11H2",
        "L5H5",
        "L7H2",
        "L25H27",
        "L10H30",
        "L3H4",
        "L12H11",
        "L3H9"
      ],
      "accuracy": 0.875,
      "accuracy_drop": 0.0625,
      "correct": 28,
      "total": 32
    }
  ]
}