{
  "method": "summed_attention_ablation_incremental",
  "model_key": "base",
  "model_name": "meta-llama/Meta-Llama-3-8B",
  "question": "inc_state",
  "question_prompt": "What state was the company incorporated in?",
  "total_tokens": 4096,
  "test_samples": 33,
  "ablation_levels": [
    5,
    10,
    20,
    30,
    40,
    50
  ],
  "heads_source": "phase2_summed_attention_results",
  "timestamp": "2026-02-05T04:59:17.411107",
  "baseline": {
    "accuracy": 0.9696969696969697,
    "correct": 32,
    "total": 33
  },
  "top_heads_ablations": [
    {
      "num_heads": 5,
      "heads": [
        [
          16,
          1
        ],
        [
          14,
          31
        ],
        [
          14,
          30
        ],
        [
          13,
          18
        ],
        [
          17,
          24
        ]
      ],
      "heads_str": [
        "L16H1",
        "L14H31",
        "L14H30",
        "L13H18",
        "L17H24"
      ],
      "accuracy": 0.7878787878787878,
      "accuracy_drop": 0.18181818181818188,
      "correct": 26,
      "total": 33
    },
    {
      "num_heads": 10,
      "heads": [
        [
          16,
          1
        ],
        [
          14,
          31
        ],
        [
          14,
          30
        ],
        [
          13,
          18
        ],
        [
          17,
          24
        ],
        [
          16,
          19
        ],
        [
          13,
          17
        ],
        [
          24,
          27
        ],
        [
          20,
          14
        ],
        [
          13,
          30
        ]
      ],
      "heads_str": [
        "L16H1",
        "L14H31",
        "L14H30",
        "L13H18",
        "L17H24",
        "L16H19",
        "L13H17",
        "L24H27",
        "L20H14",
        "L13H30"
      ],
      "accuracy": 0.9090909090909091,
      "accuracy_drop": 0.06060606060606066,
      "correct": 30,
      "total": 33
    },
    {
      "num_heads": 20,
      "heads": [
        [
          16,
          1
        ],
        [
          14,
          31
        ],
        [
          14,
          30
        ],
        [
          13,
          18
        ],
        [
          17,
          24
        ],
        [
          16,
          19
        ],
        [
          13,
          17
        ],
        [
          24,
          27
        ],
        [
          20,
          14
        ],
        [
          13,
          30
        ],
        [
          0,
          30
        ],
        [
          13,
          5
        ],
        [
          14,
          22
        ],
        [
          13,
          1
        ],
        [
          20,
          1
        ],
        [
          20,
          26
        ],
        [
          18,
          20
        ],
        [
          0,
          28
        ],
        [
          0,
          29
        ],
        [
          14,
          20
        ]
      ],
      "heads_str": [
        "L16H1",
        "L14H31",
        "L14H30",
        "L13H18",
        "L17H24",
        "L16H19",
        "L13H17",
        "L24H27",
        "L20H14",
        "L13H30",
        "L0H30",
        "L13H5",
        "L14H22",
        "L13H1",
        "L20H1",
        "L20H26",
        "L18H20",
        "L0H28",
        "L0H29",
        "L14H20"
      ],
      "accuracy": 0.5757575757575758,
      "accuracy_drop": 0.3939393939393939,
      "correct": 19,
      "total": 33
    },
    {
      "num_heads": 30,
      "heads": [
        [
          16,
          1
        ],
        [
          14,
          31
        ],
        [
          14,
          30
        ],
        [
          13,
          18
        ],
        [
          17,
          24
        ],
        [
          16,
          19
        ],
        [
          13,
          17
        ],
        [
          24,
          27
        ],
        [
          20,
          14
        ],
        [
          13,
          30
        ],
        [
          0,
          30
        ],
        [
          13,
          5
        ],
        [
          14,
          22
        ],
        [
          13,
          1
        ],
        [
          20,
          1
        ],
        [
          20,
          26
        ],
        [
          18,
          20
        ],
        [
          0,
          28
        ],
        [
          0,
          29
        ],
        [
          14,
          20
        ],
        [
          16,
          0
        ],
        [
          29,
          9
        ],
        [
          13,
          11
        ],
        [
          16,
          27
        ],
        [
          13,
          4
        ],
        [
          14,
          4
        ],
        [
          0,
          22
        ],
        [
          30,
          2
        ],
        [
          19,
          9
        ],
        [
          22,
          13
        ]
      ],
      "heads_str": [
        "L16H1",
        "L14H31",
        "L14H30",
        "L13H18",
        "L17H24",
        "L16H19",
        "L13H17",
        "L24H27",
        "L20H14",
        "L13H30",
        "L0H30",
        "L13H5",
        "L14H22",
        "L13H1",
        "L20H1",
        "L20H26",
        "L18H20",
        "L0H28",
        "L0H29",
        "L14H20",
        "L16H0",
        "L29H9",
        "L13H11",
        "L16H27",
        "L13H4",
        "L14H4",
        "L0H22",
        "L30H2",
        "L19H9",
        "L22H13"
      ],
      "accuracy": 0.5454545454545454,
      "accuracy_drop": 0.4242424242424243,
      "correct": 18,
      "total": 33
    },
    {
      "num_heads": 40,
      "heads": [
        [
          16,
          1
        ],
        [
          14,
          31
        ],
        [
          14,
          30
        ],
        [
          13,
          18
        ],
        [
          17,
          24
        ],
        [
          16,
          19
        ],
        [
          13,
          17
        ],
        [
          24,
          27
        ],
        [
          20,
          14
        ],
        [
          13,
          30
        ],
        [
          0,
          30
        ],
        [
          13,
          5
        ],
        [
          14,
          22
        ],
        [
          13,
          1
        ],
        [
          20,
          1
        ],
        [
          20,
          26
        ],
        [
          18,
          20
        ],
        [
          0,
          28
        ],
        [
          0,
          29
        ],
        [
          14,
          20
        ],
        [
          16,
          0
        ],
        [
          29,
          9
        ],
        [
          13,
          11
        ],
        [
          16,
          27
        ],
        [
          13,
          4
        ],
        [
          14,
          4
        ],
        [
          0,
          22
        ],
        [
          30,
          2
        ],
        [
          19,
          9
        ],
        [
          22,
          13
        ],
        [
          13,
          3
        ],
        [
          16,
          9
        ],
        [
          20,
          23
        ],
        [
          13,
          10
        ],
        [
          13,
          21
        ],
        [
          19,
          3
        ],
        [
          0,
          21
        ],
        [
          18,
          22
        ],
        [
          13,
          9
        ],
        [
          13,
          6
        ]
      ],
      "heads_str": [
        "L16H1",
        "L14H31",
        "L14H30",
        "L13H18",
        "L17H24",
        "L16H19",
        "L13H17",
        "L24H27",
        "L20H14",
        "L13H30",
        "L0H30",
        "L13H5",
        "L14H22",
        "L13H1",
        "L20H1",
        "L20H26",
        "L18H20",
        "L0H28",
        "L0H29",
        "L14H20",
        "L16H0",
        "L29H9",
        "L13H11",
        "L16H27",
        "L13H4",
        "L14H4",
        "L0H22",
        "L30H2",
        "L19H9",
        "L22H13",
        "L13H3",
        "L16H9",
        "L20H23",
        "L13H10",
        "L13H21",
        "L19H3",
        "L0H21",
        "L18H22",
        "L13H9",
        "L13H6"
      ],
      "accuracy": 0.48484848484848486,
      "accuracy_drop": 0.48484848484848486,
      "correct": 16,
      "total": 33
    },
    {
      "num_heads": 50,
      "heads": [
        [
          16,
          1
        ],
        [
          14,
          31
        ],
        [
          14,
          30
        ],
        [
          13,
          18
        ],
        [
          17,
          24
        ],
        [
          16,
          19
        ],
        [
          13,
          17
        ],
        [
          24,
          27
        ],
        [
          20,
          14
        ],
        [
          13,
          30
        ],
        [
          0,
          30
        ],
        [
          13,
          5
        ],
        [
          14,
          22
        ],
        [
          13,
          1
        ],
        [
          20,
          1
        ],
        [
          20,
          26
        ],
        [
          18,
          20
        ],
        [
          0,
          28
        ],
        [
          0,
          29
        ],
        [
          14,
          20
        ],
        [
          16,
          0
        ],
        [
          29,
          9
        ],
        [
          13,
          11
        ],
        [
          16,
          27
        ],
        [
          13,
          4
        ],
        [
          14,
          4
        ],
        [
          0,
          22
        ],
        [
          30,
          2
        ],
        [
          19,
          9
        ],
        [
          22,
          13
        ],
        [
          13,
          3
        ],
        [
          16,
          9
        ],
        [
          20,
          23
        ],
        [
          13,
          10
        ],
        [
          13,
          21
        ],
        [
          19,
          3
        ],
        [
          0,
          21
        ],
        [
          18,
          22
        ],
        [
          13,
          9
        ],
        [
          13,
          6
        ],
        [
          29,
          11
        ],
        [
          13,
          0
        ],
        [
          28,
          15
        ],
        [
          25,
          15
        ],
        [
          10,
          31
        ],
        [
          22,
          14
        ],
        [
          21,
          8
        ],
        [
          14,
          0
        ],
        [
          27,
          5
        ],
        [
          0,
          11
        ]
      ],
      "heads_str": [
        "L16H1",
        "L14H31",
        "L14H30",
        "L13H18",
        "L17H24",
        "L16H19",
        "L13H17",
        "L24H27",
        "L20H14",
        "L13H30",
        "L0H30",
        "L13H5",
        "L14H22",
        "L13H1",
        "L20H1",
        "L20H26",
        "L18H20",
        "L0H28",
        "L0H29",
        "L14H20",
        "L16H0",
        "L29H9",
        "L13H11",
        "L16H27",
        "L13H4",
        "L14H4",
        "L0H22",
        "L30H2",
        "L19H9",
        "L22H13",
        "L13H3",
        "L16H9",
        "L20H23",
        "L13H10",
        "L13H21",
        "L19H3",
        "L0H21",
        "L18H22",
        "L13H9",
        "L13H6",
        "L29H11",
        "L13H0",
        "L28H15",
        "L25H15",
        "L10H31",
        "L22H14",
        "L21H8",
        "L14H0",
        "L27H5",
        "L0H11"
      ],
      "accuracy": 0.6060606060606061,
      "accuracy_drop": 0.36363636363636365,
      "correct": 20,
      "total": 33
    }
  ],
  "random_heads_ablations": [
    {
      "num_heads": 5,
      "heads": [
        [
          21,
          23
        ],
        [
          3,
          24
        ],
        [
          0,
          31
        ],
        [
          25,
          3
        ],
        [
          8,
          31
        ]
      ],
      "heads_str": [
        "L21H23",
        "L3H24",
        "L0H31",
        "L25H3",
        "L8H31"
      ],
      "accuracy": 0.9696969696969697,
      "accuracy_drop": 0.0,
      "correct": 32,
      "total": 33
    },
    {
      "num_heads": 10,
      "heads": [
        [
          21,
          23
        ],
        [
          3,
          24
        ],
        [
          0,
          31
        ],
        [
          25,
          3
        ],
        [
          8,
          31
        ],
        [
          8,
          0
        ],
        [
          7,
          10
        ],
        [
          4,
          20
        ],
        [
          24,
          30
        ],
        [
          3,
          14
        ]
      ],
      "heads_str": [
        "L21H23",
        "L3H24",
        "L0H31",
        "L25H3",
        "L8H31",
        "L8H0",
        "L7H10",
        "L4H20",
        "L24H30",
        "L3H14"
      ],
      "accuracy": 0.9696969696969697,
      "accuracy_drop": 0.0,
      "correct": 32,
      "total": 33
    },
    {
      "num_heads": 20,
      "heads": [
        [
          21,
          23
        ],
        [
          3,
          24
        ],
        [
          0,
          31
        ],
        [
          25,
          3
        ],
        [
          8,
          31
        ],
        [
          8,
          0
        ],
        [
          7,
          10
        ],
        [
          4,
          20
        ],
        [
          24,
          30
        ],
        [
          3,
          14
        ],
        [
          22,
          31
        ],
        [
          25,
          2
        ],
        [
          30,
          3
        ],
        [
          18,
          14
        ],
        [
          2,
          31
        ],
        [
          20,
          0
        ],
        [
          14,
          6
        ],
        [
          1,
          6
        ],
        [
          1,
          4
        ],
        [
          3,
          5
        ]
      ],
      "heads_str": [
        "L21H23",
        "L3H24",
        "L0H31",
        "L25H3",
        "L8H31",
        "L8H0",
        "L7H10",
        "L4H20",
        "L24H30",
        "L3H14",
        "L22H31",
        "L25H2",
        "L30H3",
        "L18H14",
        "L2H31",
        "L20H0",
        "L14H6",
        "L1H6",
        "L1H4",
        "L3H5"
      ],
      "accuracy": 0.9696969696969697,
      "accuracy_drop": 0.0,
      "correct": 32,
      "total": 33
    },
    {
      "num_heads": 30,
      "heads": [
        [
          21,
          23
        ],
        [
          3,
          24
        ],
        [
          0,
          31
        ],
        [
          25,
          3
        ],
        [
          8,
          31
        ],
        [
          8,
          0
        ],
        [
          7,
          10
        ],
        [
          4,
          20
        ],
        [
          24,
          30
        ],
        [
          3,
          14
        ],
        [
          22,
          31
        ],
        [
          25,
          2
        ],
        [
          30,
          3
        ],
        [
          18,
          14
        ],
        [
          2,
          31
        ],
        [
          20,
          0
        ],
        [
          14,
          6
        ],
        [
          1,
          6
        ],
        [
          1,
          4
        ],
        [
          3,
          5
        ],
        [
          7,
          5
        ],
        [
          7,
          20
        ],
        [
          17,
          4
        ],
        [
          20,
          13
        ],
        [
          1,
          1
        ],
        [
          19,
          0
        ],
        [
          6,
          17
        ],
        [
          24,
          8
        ],
        [
          22,
          2
        ],
        [
          23,
          25
        ]
      ],
      "heads_str": [
        "L21H23",
        "L3H24",
        "L0H31",
        "L25H3",
        "L8H31",
        "L8H0",
        "L7H10",
        "L4H20",
        "L24H30",
        "L3H14",
        "L22H31",
        "L25H2",
        "L30H3",
        "L18H14",
        "L2H31",
        "L20H0",
        "L14H6",
        "L1H6",
        "L1H4",
        "L3H5",
        "L7H5",
        "L7H20",
        "L17H4",
        "L20H13",
        "L1H1",
        "L19H0",
        "L6H17",
        "L24H8",
        "L22H2",
        "L23H25"
      ],
      "accuracy": 0.8787878787878788,
      "accuracy_drop": 0.09090909090909094,
      "correct": 29,
      "total": 33
    },
    {
      "num_heads": 40,
      "heads": [
        [
          21,
          23
        ],
        [
          3,
          24
        ],
        [
          0,
          31
        ],
        [
          25,
          3
        ],
        [
          8,
          31
        ],
        [
          8,
          0
        ],
        [
          7,
          10
        ],
        [
          4,
          20
        ],
        [
          24,
          30
        ],
        [
          3,
          14
        ],
        [
          22,
          31
        ],
        [
          25,
          2
        ],
        [
          30,
          3
        ],
        [
          18,
          14
        ],
        [
          2,
          31
        ],
        [
          20,
          0
        ],
        [
          14,
          6
        ],
        [
          1,
          6
        ],
        [
          1,
          4
        ],
        [
          3,
          5
        ],
        [
          7,
          5
        ],
        [
          7,
          20
        ],
        [
          17,
          4
        ],
        [
          20,
          13
        ],
        [
          1,
          1
        ],
        [
          19,
          0
        ],
        [
          6,
          17
        ],
        [
          24,
          8
        ],
        [
          22,
          2
        ],
        [
          23,
          25
        ],
        [
          14,
          2
        ],
        [
          7,
          7
        ],
        [
          15,
          5
        ],
        [
          19,
          31
        ],
        [
          9,
          2
        ],
        [
          27,
          10
        ],
        [
          29,
          10
        ],
        [
          0,
          6
        ],
        [
          25,
          22
        ],
        [
          27,
          7
        ]
      ],
      "heads_str": [
        "L21H23",
        "L3H24",
        "L0H31",
        "L25H3",
        "L8H31",
        "L8H0",
        "L7H10",
        "L4H20",
        "L24H30",
        "L3H14",
        "L22H31",
        "L25H2",
        "L30H3",
        "L18H14",
        "L2H31",
        "L20H0",
        "L14H6",
        "L1H6",
        "L1H4",
        "L3H5",
        "L7H5",
        "L7H20",
        "L17H4",
        "L20H13",
        "L1H1",
        "L19H0",
        "L6H17",
        "L24H8",
        "L22H2",
        "L23H25",
        "L14H2",
        "L7H7",
        "L15H5",
        "L19H31",
        "L9H2",
        "L27H10",
        "L29H10",
        "L0H6",
        "L25H22",
        "L27H7"
      ],
      "accuracy": 0.8787878787878788,
      "accuracy_drop": 0.09090909090909094,
      "correct": 29,
      "total": 33
    },
    {
      "num_heads": 50,
      "heads": [
        [
          21,
          23
        ],
        [
          3,
          24
        ],
        [
          0,
          31
        ],
        [
          25,
          3
        ],
        [
          8,
          31
        ],
        [
          8,
          0
        ],
        [
          7,
          10
        ],
        [
          4,
          20
        ],
        [
          24,
          30
        ],
        [
          3,
          14
        ],
        [
          22,
          31
        ],
        [
          25,
          2
        ],
        [
          30,
          3
        ],
        [
          18,
          14
        ],
        [
          2,
          31
        ],
        [
          20,
          0
        ],
        [
          14,
          6
        ],
        [
          1,
          6
        ],
        [
          1,
          4
        ],
        [
          3,
          5
        ],
        [
          7,
          5
        ],
        [
          7,
          20
        ],
        [
          17,
          4
        ],
        [
          20,
          13
        ],
        [
          1,
          1
        ],
        [
          19,
          0
        ],
        [
          6,
          17
        ],
        [
          24,
          8
        ],
        [
          22,
          2
        ],
        [
          23,
          25
        ],
        [
          14,
          2
        ],
        [
          7,
          7
        ],
        [
          15,
          5
        ],
        [
          19,
          31
        ],
        [
          9,
          2
        ],
        [
          27,
          10
        ],
        [
          29,
          10
        ],
        [
          0,
          6
        ],
        [
          25,
          22
        ],
        [
          27,
          7
        ],
        [
          5,
          9
        ],
        [
          23,
          21
        ],
        [
          11,
          3
        ],
        [
          5,
          5
        ],
        [
          7,
          2
        ],
        [
          25,
          26
        ],
        [
          10,
          30
        ],
        [
          3,
          4
        ],
        [
          12,
          12
        ],
        [
          3,
          9
        ]
      ],
      "heads_str": [
        "L21H23",
        "L3H24",
        "L0H31",
        "L25H3",
        "L8H31",
        "L8H0",
        "L7H10",
        "L4H20",
        "L24H30",
        "L3H14",
        "L22H31",
        "L25H2",
        "L30H3",
        "L18H14",
        "L2H31",
        "L20H0",
        "L14H6",
        "L1H6",
        "L1H4",
        "L3H5",
        "L7H5",
        "L7H20",
        "L17H4",
        "L20H13",
        "L1H1",
        "L19H0",
        "L6H17",
        "L24H8",
        "L22H2",
        "L23H25",
        "L14H2",
        "L7H7",
        "L15H5",
        "L19H31",
        "L9H2",
        "L27H10",
        "L29H10",
        "L0H6",
        "L25H22",
        "L27H7",
        "L5H9",
        "L23H21",
        "L11H3",
        "L5H5",
        "L7H2",
        "L25H26",
        "L10H30",
        "L3H4",
        "L12H12",
        "L3H9"
      ],
      "accuracy": 0.8181818181818182,
      "accuracy_drop": 0.1515151515151515,
      "correct": 27,
      "total": 33
    }
  ]
}